Metadata-Version: 2.1
Name: JsToPy
Version: 0.1.5
Summary: A library that add to python some js functions.
Home-page: https://github.com/F1reWs/JsToPy
Author: Firew
Author-email: road.of.programming@gmail.com
License: MIT
Classifier: Programming Language :: Python :: 3
Classifier: License :: OSI Approved :: MIT License
Classifier: Operating System :: OS Independent
